<commerce_point>
	<node>
		<header>
			<background lang="en-GB" default="true">http://scee-home.playstation.net/e.home/hosted/CommercePoints/Thumbnails/starsyellow_bg_scee.png</background>
		</header>
	<node>
				<header>
			<name lang="en-GB" default="true">Playstation®Home</name>
			<name lang="fr-FR" >Playstation®Home</name>
			<name lang="it-IT" >Playstation®Home</name>
			<name lang="de-DE" >Playstation®Home</name>
			<name lang="es-ES" >Playstation®Home</name>
			<name lang="es-ES" >Playstation®Home</name>
			<thumbnail lang="en-GB" default="true"> http://scee-home.playstation.net/e.home/hosted/CommercePoints/Thumbnails/HomeStore.png</thumbnail>
                  <background lang="en-GB" default="true">http://scee-home.playstation.net/e.home/hosted/CommercePoints/Thumbnails/starsyellow_bg_scee.png</background>
				</header>
								<node type="objects">
				<header>
					<name lang="en-GB" default="true">Male</name>
					<name lang="fr-FR">Homme</name>
					<name lang="de-DE">Männlich</name>
					<name lang="it-IT">Maschio</name>
					<name lang="es-ES">Hombre</name>
					<thumbnail lang="en-GB" default="true" useOsdColour="true">http://scee-home.playstation.net/e.home/hosted/CommercePoints/Thumbnails/male.dds</thumbnail>
						<background lang="en-GB" default="true">http://scee-home.playstation.net/e.home/hosted/CommercePoints/Thumbnails/starsyellow_bg_scee.png</background>
				</header>
									<!-- Egyptian Bundles M  -->
					<object>3EC2C7C1-82DE4256-B0446CDF-CA4AE6B1</object> 
					<object>C8FEB199-D9ED411F-804E95E7-F93E1F46</object> 
					<object>5D39203F-D61E43F3-9DE6DC9E-62B3C61F</object> 
					<object>193723AA-3702470C-954F691D-DD9AFAAD</object> 
					<object>8EF33AFD-24D14BED-98F96073-636B5779</object> 
					 </node>
					 	<node type="objects">
				<header>
					<name lang="en-GB" default="true">Female</name>
					<name lang="fr-FR" >Femme</name>
					<name lang="it-IT" >Femmina</name>
					<name lang="de-DE" >Weiblich</name>
					<name lang="es-ES" >Mujer</name>
					<thumbnail lang="en-GB" default="true" useOsdColour="true">http://scee-home.playstation.net/e.home/hosted/CommercePoints/Thumbnails/female.dds</thumbnail>
						<background lang="en-GB" default="true">http://scee-home.playstation.net/e.home/hosted/CommercePoints/Thumbnails/starsyellow_bg_scee.png</background>
				</header>
									<!-- Egyptian Bundles F  -->
					<object>3EC2C7C1-82DE4256-B0446CDF-CA4AE6B1</object> 
					<object>C8FEB199-D9ED411F-804E95E7-F93E1F46</object> 
					<object>A333F69C-9D9E4821-8F3FB349-59D35653</object> 
					<object>E2149A25-EAF44A86-A606B71A-5B4386E1</object> 
					<object>FFA3A7FD-D69A4BCC-9BC2CAAC-261F4AB8</object> 
			 </node>
			 			<node type="objects">
				<header>
        <name lang="en-GB" default="true">Furniture</name>
        <name lang="fr-FR" >Meubles</name>
        <name lang="it-IT" >Mobili</name>
        <name lang="de-DE" >Möbel</name>
        <name lang="es-ES" >Muebles</name>
			<thumbnail lang="en-GB" default="true" useOsdColour="true"> http://scee-home.playstation.net/e.home/hosted/CommercePoints/Thumbnails/Furniture_jp.dds</thumbnail>
					<background default="true">http://scee-home.playstation.net/e.home/hosted/CommercePoints/Thumbnails/starsyellow_bg_scee.png</background> 
				</header>
      				<!-- Cutthroats Music Player -->		
				<object>A9D6B4C3-F1264D87-AF01DFBB-EBC0FEBD</object>
				        <!-- Playground Boom Box  -->
        <object>11837619-BBE14BA4-9511F580-379727E3</object>
		<object>3E347AFC-EC214633-85EBBB18-D3255905</object>	        <!-- Orange Cat -->
						                <!-- Animated Tesla coil -->
        <object>7A20BE60-36FC4CA0-80715EE4-C13F2487</object>
                <!-- Cherry Blossom Tree -->
        <object>DF43975B-E0FA4BF8-8555FDAA-96686777</object>
                <!-- Animated DJ Light set -->
        <object>235D6F2B-67A04998-84640318-4F6F305F</object>
                <!-- Gypsy Fortune Teller -->
        <object>D2D98678-46244DF0-B2164C34-9D1F1389</object>
                <!-- Mysterious Doll  -->
        <object>FDF80D8F-FA104E48-918DBE6E-DFA33861</object>
			</node>
	  <node type="objects">
        <header>
          <name lang="en-GB" default="true">Personal Space</name>
          <name lang="fr-FR" >Espace personnel</name>
          <name lang="it-IT" >Spazio personale</name>
          <name lang="de-DE" >Home-Apartment</name>
          <name lang="es-ES" >Espacio personal</name>
          <thumbnail lang="en-GB" default="true" useOsdColour="true">http://scee-home.playstation.net/e.home/hosted/CommercePoints/Thumbnails/apartment_scee.dds</thumbnail>
						<background lang="en-GB" default="true">http://scee-home.playstation.net/e.home/hosted/CommercePoints/Thumbnails/starsyellow_bg_scee.png</background>
        </header>
                <!--Playground Apartment-->
		<object>A02FA240-BA2E4816-88BAB4F3-A120FD4E</object>
	    <!--7thMay Log Cabin-->
	    <object>77D9E3EF-02A74DA9-BD77FBBD-91407A88</object>
	            <!--Treehouse Apartment-->  
        <object>B9867B6D-98174DB2-A27DA8F7-32C51251</object>
                <!--Japanese Apartment -->
		<object>16609817-77F646D8-878789D7-135196C6</object>
	 </node>
	 	   <node type="objects">
				<header>
					<name lang="en-GB" default="true">Companions</name>
					<name lang="fr-FR" >Compagne</name>
					<name lang="it-IT" >Compagno</name>
					<name lang="de-DE" >Begleiter</name>
					<name lang="es-ES" >Comrade</name>
					<thumbnail lang="en-GB" default="true" useOsdColour="true">http://scee-home.playstation.net/e.home/hosted/CommercePoints/Thumbnails/companion.dds</thumbnail>
						<background lang="en-GB" default="true">http://scee-home.playstation.net/e.home/hosted/CommercePoints/Thumbnails/starsyellow_bg_scee.png</background>
				</header>
								<!-- Farmyard companions - Bundle, Chick, Sheep, Pig, Donkey -->
				<object>91840E0E-04D44E64-8477BD98-00D03035</object>
			    <object>3B43A880-B6E94691-B328DC39-7FB39809</object>
				<object>7FD066CA-0274496E-857AB154-A3835AA9</object>
				<object>E3B06E8E-D81A4522-B2F7E9C1-B567E2B0</object>
				<object>81087D4B-EA5742B4-8AD989AC-F568462C</object>
				 <!-- Fox companion -->
                <object>0B68AC71-39AA467E-95924C22-2A19917F</object>
                	    <!-- Pet Dragon Companion -->
		<object>625728D3-47474705-924F40D2-B9EC55EB</object>
                				<!-- RacingCar companion -->
                <object>4B709E0F-25A944A4-AB3195D7-926F3239</object>
			</node>
	 	 </node>
	 	  <node type="objects">
	<header>
			<name lang="en-GB" default="true">Board Games</name>
			<name lang="fr-FR" >Jeux de société</name>
			<name lang="it-IT" >Giochi da tavolo</name>
			<name lang="de-DE" >Brettspiele</name>
			<name lang="es-ES" >Juegos de mesa</name>
			<thumbnail lang="en-GB" default="true">http://scee-home.playstation.net/e.home/hosted/CommercePoints/Thumbnails/reddice_scee.png</thumbnail>
	<background lang="en-GB" default="true">http://scee-home.playstation.net/e.home/hosted/CommercePoints/Thumbnails/starsyellow_bg_scee.png</background>
	</header>
        <!-- Checkers -->
        <object>657CF753-A11A4082-8BF4EC6D-5D9346F0</object>
        <object>501664A1-951E4CF5-A7C3E343-3581D4D6</object>
        <object>C69DAF52-E02A4835-8B6D4B7B-7C8C1DE0</object>
        <object>4EF3DE0D-3E6442D0-8679FED6-F4832B6F</object>
        <object>3964377E-06B54F36-A27A4628-948DC59B</object>
        <!-- Chess -->
        <object>4F269B85-34CB4615-99080E5E-1C6ADBFC</object>
        <object>4436A967-8B7C419D-9AD37BAB-3FA136F7</object>
        <object>23052E0D-D9C54F4E-9FA63EF4-52952F41</object>
        <object>4A6B28FF-1E9044B7-91AEE3D5-E9F21740</object>
        <object>4BD0B039-D06241DB-89024A65-97F0536F</object>
       <!-- Solitaire tables -->
       <object>D619F591-03DE4B60-BC01BF0C-47A609CF</object>
       <object>60E8CABA-70E24819-87F0AC4E-9B42363F</object>
       <object>E278013F-67444757-BB478237-1F178C8D</object>
       <object>EF3928AA-CA9843C2-B978BB8B-6E37EAC1</object>
       <object>8F8B97F0-C6D141D0-832640B4-CDF269DD</object>
         <!--Solitaire Card Minigame (original) -->
        <object>A294A886-F4AD4FB8-A309A8C7-0968FE50</object>
        <!--Dice  -->
        <object>00000000-00000000-000000F3-00000001</object>
  </node>
  	<node>
				<header>
			<name lang="en-GB" default="true">PlayStation Home Arcade</name>
			<name lang="fr-FR" >PlayStation Home Arcade</name>
			<name lang="it-IT" >PlayStation Home Arcade</name>
			<name lang="de-DE" >PlayStation Home Arcade</name>
			<name lang="es-ES" >PlayStation Home Arcade</name>
			<name lang="es-ES" >PlayStation Home Arcade</name>
			<thumbnail lang="en-GB" default="true"> http://scee-home.playstation.net/e.home/hosted/CommercePoints/Thumbnails/HAP_scee.png</thumbnail>
                  <background lang="en-GB" default="true">http://scee-home.playstation.net/e.home/hosted/CommercePoints/Thumbnails/starsyellow_bg_scee.png</background>
				</header>
					  <node type="products">
      <header>
        <name lang="en-GB" default="true">PlayStation Home Arcade for PS Vita</name>
        <name lang="fr-FR" >PlayStation Home Arcade (PS Vita)</name>
        <name lang="it-IT" >PlayStation Home Arcade (PS Vita)</name>
        <name lang="de-DE" >PlayStation Home Arcade (PS Vita)</name>
        <name lang="es-ES" >PlayStation Home Arcade(PS Vita)</name>
        <thumbnail lang="en-GB" default="true">http://scee-home.playstation.net/e.home/hosted/CommercePoints/Thumbnails/psvita_scee.png</thumbnail>
                  <background lang="en-GB" default="true">http://scee-home.playstation.net/e.home/hosted/CommercePoints/Thumbnails/starsyellow_bg_scee.png</background>
      </header>
                <!-- Home Arcade Player -->
         <product category="EP9000-PCSF00228_00">EP9000-PCSF00228_00-HAPFINAL00000000</product>
            </node>	
      <node type="objects">
        <header>
          <name lang="en-GB">Arcade Cabinets</name>
        <name lang="fr-FR" >Console Arcade</name>
        <name lang="it-IT" >Videogioco Arcade</name>
        <name lang="de-DE" >Arcade Automat</name>
        <name lang="es-ES" >Máquina Recreativa</name>
          <thumbnail lang="en-GB" default="true" useOsdColour="true">http://scee-home.playstation.net/e.home/hosted/CommercePoints/Thumbnails/arcade.dds</thumbnail>
                  <background lang="en-GB" default="true">http://scee-home.playstation.net/e.home/hosted/CommercePoints/Thumbnails/starsyellow_bg_scee.png</background>
      </header>
         <!-- Scribbleshooter -->
        <object>07EC34C7-67984277-916874A1-E24A9A98</object>
         <!-- Madblocker -->
        <object>EFD9F073-E97242B9-91AFB5AC-29B1D6D8</object>
        <!-- Frogger -->
        <object>5D09B676-E103497D-9940B7DE-37AAEBC6</object>
        <!-- Time Pilot -->
        <object>989F10CA-319A4A94-BEE03773-F265360F</object>
          </node>
              </node>
	<node type="objects">
		<header >
			<name lang="en-GB" default="true">Defiance</name>
			<name lang="fr-FR">Defiance</name>
			<name lang="de-DE">Defiance</name>
			<name lang="it-IT">Defiance</name>
			<name lang="es-ES">Defiance</name>
			<thumbnail lang="en-GB" default="true" useOsdColour="false">http://scee-home.playstation.net/e.home/hosted/CommercePoints/Thumbnails/defiance_scee.png</thumbnail>
						<background lang="en-GB" default="true">http://scee-home.playstation.net/e.home/hosted/CommercePoints/Thumbnails/starsyellow_bg_scee.png</background>
		</header>		
		<!-- Defiance items -->   
    <object>56A71E86-AB534E9E-88CE5780-676DEE0A</object>
	<object>B7A66E43-0BEB43E2-BCD3CDCB-5DDC04F0</object>
	<object>C9C9459B-12B84F70-88506F7A-7FE9E747</object>
	<object>86815139-09624C46-98744CA5-2A7796F7</object>
	<object>01D2A2B9-FE774417-A2882706-6DD08AFB</object>
	<object>5A6C2245-89A34191-BC848BCF-DBBB1A5D</object>
	<object>3C198F44-CA004214-ADF42798-4E7227E5</object>
	<object>E1ADA903-173642C1-9F878AE7-902F1B8D</object>
		<object>81266F39-BF334ADD-83A75CEF-9ACDE2E8</object>
			</node>
						<node type="objects">
		<header >
			<name lang="en-GB" default="true">Doctor Who</name>
			<name lang="fr-FR">Doctor Who</name>
			<name lang="de-DE">Doctor Who</name>
			<name lang="it-IT">Doctor Who</name>
			<name lang="es-ES">Doctor Who</name>
			<thumbnail lang="en-GB" default="true" useOsdColour="false">http://scee-home.playstation.net/e.home/hosted/CommercePoints/Thumbnails/doctorwho1_scee.png</thumbnail>
						<background lang="en-GB" default="true">http://scee-home.playstation.net/e.home/hosted/CommercePoints/Thumbnails/starsyellow_bg_scee.png</background>
		</header>		
		<!-- Doctor Who Wave 1 -->   
    <object>3F1FCE31-4DA04AE9-9A2533B4-CF7AC1A6</object><!--Doctor Who - Wave One Bundle-->
	<object>D6F5543E-17FD42D7-840D5F06-61FAEDA3</object><!--Doctor Who TARDIS - Private Space and Clubhouse Bundle-->
	<object>19680F44-862C45FD-B89D1EC1-D38EFF15</object><!--Doctor Who - The Eleventh Doctor Costume-->
	<object>8864DBE4-E39247BC-BAFE27DE-FBB72077</object><!--Doctor Who - River Song Costume-->
	<object>A7E217D4-CDE54873-8A4EAD92-A5E4EE24</object><!--Doctor Who - Silent Costume-->
	<object>B1B1F6F2-0C3742DE-A569E77B-2F09CA43</object><!--Doctor Who - Silurian Costume with mask-->
	<object>61D0D7DA-2A4F4FA3-9A9C1ABE-57D0D842</object><!--Doctor Who - The Eleventh Doctor's Sonic Screwdriver-->
	<object>C64FBC16-79E4474F-B1D5DBAE-340A6ACC</object><!--Doctor Who - River Song's PDA-->
		<object>6BB6D122-1ED8401A-A1DDCBDE-F52ED94B</object><!--Doctor Who - Cybermat companion-->
			</node>
		<node type="objects">
		<header >
			<name lang="en-GB" default="true">Desert Haven Clubhouse</name>
			<name lang="fr-FR">Club Oasis du désert</name>
			<name lang="de-DE">Desert Haven Wüstenoase	</name>
			<name lang="it-IT">Rifugio del deserto Clubhouse</name>
			<name lang="es-ES">Remanso del desierto Clubhouse</name>
			<thumbnail lang="en-GB" default="true" useOsdColour="false">http://scee-home.playstation.net/e.home/hosted/CommercePoints/Thumbnails/deserthaven_scee.png</thumbnail>
						<background lang="en-GB" default="true">http://scee-home.playstation.net/e.home/hosted/CommercePoints/Thumbnails/starsyellow_bg_scee.png</background>
		</header>		
		    	    <!--Clubhouse Slot-->
	    <object>63969967-334F4FD7-A57D0768-DA16D0FC</object>
		<!-- Desert Haven Clubhouse -->   
<object>865345B3-D99F41D6-8C2E011C-D38E78F1</object>
		<!-- Desert Haven Furniture-->   
<object>6B6420C6-9C154E6E-BED8A39B-FA0A0892</object>
<object>0E0B52C4-57CF416A-B6109970-EEDC4DE1</object>
<object>30D9DD62-180D414C-88A7A596-1012DBEA</object>
<object>DDDCCF3C-8FD24536-8F46B08E-DA619795</object>
<object>AB074EFE-6ED84024-87E249A9-33C26F4A</object>
			</node>
						<node>
			<header>
					<name lang="en-GB" default="true">Granzella</name>
					<name lang="fr-FR">Granzella</name>
					<name lang="de-DE">Granzella</name>
					<name lang="it-IT">Granzella</name>
					<name lang="es-ES">Granzella</name>
			<thumbnail lang="en-GB" default="true" useOsdColour="false"> http://scee-home.playstation.net/e.home/hosted/CommercePoints/Thumbnails/granzella_scee.png</thumbnail>
					<background default="true">http://scee-home.playstation.net/e.home/hosted/CommercePoints/Thumbnails/starsyellow_bg_scee.png</background> 
			</header>
		 <node type="objects">
      <header>
        <name lang="en-GB" default="true">Female</name>
        <name lang="fr-FR" >Femme</name>
        <name lang="it-IT" >Femmina</name>
        <name lang="de-DE" >Weiblich</name>
        <name lang="es-ES" >Mujer</name>
        <thumbnail lang="en-GB" default="true" useOsdColour="true">http://scee-home.playstation.net/e.home/hosted/CommercePoints/Thumbnails/female.dds</thumbnail>
						<background lang="en-GB" default="true">http://scee-home.playstation.net/e.home/hosted/CommercePoints/Thumbnails/starsyellow_bg_scee.png</background>
      </header> 
        <!-- Casual#2 F -->   
<object>2B817705-75654FA9-AEEA16D9-DBE0E500</object> 
<object>2D10549B-EE5040F6-868F6980-78C0B368</object>
<object>2DEC8F60-2ECD449C-A082D57D-BCFF7457</object>
<!-- Hostess F -->   
<object>400645E6-21B64488-8C263413-1736AF7A</object>
<object>403EB1DE-BBBA4EDF-B1B45B43-49E9F6FC</object>
<object>42D0BA78-F14043D4-8747217E-43E2B490</object>
<object>430D256C-4EF54AFE-8C2C8BE0-7AB37C1E</object>
<object>46B86C73-4B0F4C16-92D880F1-7EF75151</object>
<object>48585C97-2EF14160-A08C72D6-924662FA</object>
<object>489DBBB3-E49D49E9-BF78378E-EBFD3FBE</object>
<object>4A1C14F0-A23A4E63-BAD65083-CBB4FCB0</object>
<object>4BFAC34D-54BA4F17-A5C4E997-387CF787</object>
<object>4C208F34-75544649-AF6E78C4-796B867A</object>
<object>4C49380A-93E74488-A07E48CA-4EC7CA67</object>
<object>4F8E0544-43414B4F-91642042-102273D3</object>
<object>521E566C-8A50438E-B7D3B10C-6FC57887</object>
<object>57EFC6C3-AC05497E-8085DC0B-AF1BF451</object>
<object>58947A02-B8C94C28-B89A7077-C379A2D0</object>
<object>5AFDE995-C96F4EEB-A36E18EB-60C7C205</object>
<object>5FA47415-67204442-B3F8C979-078372A9</object>
<object>6018B7BC-875348E7-BF8F9D19-66E94DE6</object>
<object>61B4CD62-74C84EAF-A6A7AB16-0DEF09A2</object>
<object>61BC055E-707F4938-B2829492-C4922269</object>
<object>6AEC44A4-32C242DB-9870C0DD-59549AF9</object>
<object>6B654A07-BB9B455C-B6E138F7-C141C8A6</object>
<object>6CEE74E8-C1664E0D-89D04CCE-B002EF14</object>
<object>6D7A8E11-8B2C4F40-A0F86118-B63C2571</object>
<object>6DD421CD-8D674691-904B267E-14A43B40</object>
<object>6EBAD91C-D37C40CD-971B4C26-3CBC8B07</object>
<object>743238DF-7D074E5E-8E9ABF2A-E84DCF40</object>
<object>744FADF2-6661434D-984CBCB8-0C633F7C</object>
<object>77B566F4-F7594F1D-8111A20F-0B235C20</object>
<object>77ECCE1A-AF20485C-A78040A6-E5B5C522</object>
<object>77F1CE87-E35A430D-B6C85E06-1A090714</object>
<object>79B74CA4-8F0D49F1-89EE393A-9D893FCB</object>
<object>87E1B235-E9F94E1B-97BBBC2F-35D3CBA1</object>
<object>88AF3612-4A294E0A-9979B9A8-ADCF850D</object>
<object>8BFA373E-EB2C4639-83B8AF0E-ABB4F4F4</object>
<object>8D82F8FF-B8EC4D14-81E5DC98-BB848B79</object>
<object>8E34137F-24F24E66-AAA3EAB3-6D5F5E64</object>
<object>8E9C420B-A112457C-A161BB80-0206A67D</object>
<object>8EFC6471-55AB41C0-8A83D643-1E7E13AD</object>
						</node>
	</node>
				<node type="objects">
				<header>
				  <name lang="en-GB" default="true">MyBedroom</name>
				  <name lang="fr-FR" >MyBedroom</name>
				  <name lang="it-IT" >MyBedroom</name>
				  <name lang="de-DE" >MyBedroom</name>
				  <name lang="es-ES" >MyBedroom</name>
				  <thumbnail lang="en-GB" default="true">http://scee-home.playstation.net/e.home/hosted/CommercePoints/Thumbnails/mybedroom_scee.png</thumbnail>
				  <background lang="en-GB" default="true">http://scee-home.playstation.net/e.home/hosted/CommercePoints/Thumbnails/starsyellow_bg_scee.png</background>
				</header>
		<!-- MyBedroom Burgundy 17/4/13 --> 
<object>623E0DD8-0E8D4C58-B3D5A2A7-A7618C92</object>
<object>A766DEE7-68854BC7-8CB5ED66-8FC05A4D</object>
<object>9677B8E4-98514B71-8EF072E4-C77BDFA5</object>
<object>0535504F-67394D74-B06B457F-DCB26867</object>
<object>A15A7BC1-4D224F65-8817A452-8581A854</object>
<object>A5C5BC2D-E2AB4F66-A0D2A845-3D111335</object>
<object>2866C75A-52194780-85152AAD-5A47AC13</object>
<object>DCE3A061-B08C4717-8475F221-4A74A96F</object>
<object>570D96EE-690C4B53-B09C1850-B8B1195E</object>
<object>83A9771F-54A0454C-AA734CF1-4CF3B8E6</object>
<object>3FA32179-1BF44376-8EF22E33-EA06813F</object>
<object>27627BE5-0B954391-9947A841-2AA39E6E</object>
<object>7DB6C070-9E0D41EE-99A0590C-9CABBED4</object>
				<!-- MyBedroom --> 
<object>AA65ADB6-F3EC4949-9DD90FF2-7C48DA42</object>
<object>18DA10AF-79434548-A0CCB1A1-18C702C1</object>
<object>C39E89A3-4D224E74-A90A6084-25404ABD</object>
<object>0D9E2DE8-00F64A73-B3FD0805-38E2EDC5</object>
<object>CF75025E-FDE7477E-A35221B5-13F22A51</object>
<object>41A0FAC3-500A4DDA-82DC001D-81ED3307</object>
<object>5D14923D-ABA4494B-91960F25-C9E8C8CB</object>
<object>44EBD903-1BFE4252-A48C640B-FB12D5AA</object>
<object>DDB78165-D0754A63-A98CD834-A0FDF0BF</object>
<object>40871FD0-D8974AA8-B70304B3-891859F6</object>
<object>93D85698-B5224152-B3580998-5D4A26A5</object>
<object>42A518DC-10764E05-8F6B25AE-0BE34CED</object>
<object>5F48D7E3-53074C91-AF0B9FB1-290037A6</object>
			</node>
    <node>
				<header>
				  <name lang="en-GB" default="true">Billabong</name>
				  <name lang="fr-FR" >Billabong</name>
				  <name lang="it-IT" >Billabong</name>
				  <name lang="de-DE" >Billabong</name>
				  <name lang="es-ES" >Billabong</name>
				  <thumbnail lang="en-GB" default="true">http://scee-home.playstation.net/e.home/hosted/CommercePoints/Thumbnails/billabong-logo.png</thumbnail>
				  <background lang="en-GB" default="true">http://scee-home.playstation.net/e.home/hosted/CommercePoints/Thumbnails/starsyellow_bg_scee.png</background>
				</header>
										<node type="objects">
				<header>
					<name lang="en-GB" default="true">Male</name>
					<name lang="fr-FR">Homme</name>
					<name lang="de-DE">Männlich</name>
					<name lang="it-IT">Maschio</name>
					<name lang="es-ES">Hombre</name>
					<thumbnail lang="en-GB" default="true" useOsdColour="true">http://scee-home.playstation.net/e.home/hosted/CommercePoints/Thumbnails/male.dds</thumbnail>
						<background lang="en-GB" default="true">http://scee-home.playstation.net/e.home/hosted/CommercePoints/Thumbnails/starsyellow_bg_scee.png</background>
				</header>
			<!-- Billabong 17/4/13 M --> 
<object>C2B23EF8-90964A59-A76449A9-197870C4</object> <!-- head -->
<object>AE65A24B-87E248FC-996822C2-EBC7FF6B</object> <!-- legs -->
<object>515824B0-A06A4C2A-8E83892C-1A506118</object> <!-- torso -->
<object>A7CE34DB-B9A042AB-BE8BA1B2-1B30265D</object> <!-- torso -->
<object>2CE1F32D-7649493A-B898ABE5-4BE830A9</object> <!-- torso -->
		</node>
			<node type="objects">
				<header>
					<name lang="en-GB" default="true">Female</name>
					<name lang="fr-FR" >Femme</name>
					<name lang="it-IT" >Femmina</name>
					<name lang="de-DE" >Weiblich</name>
					<name lang="es-ES" >Mujer</name>
					<thumbnail lang="en-GB" default="true" useOsdColour="true">http://scee-home.playstation.net/e.home/hosted/CommercePoints/Thumbnails/female.dds</thumbnail>
						<background lang="en-GB" default="true">http://scee-home.playstation.net/e.home/hosted/CommercePoints/Thumbnails/starsyellow_bg_scee.png</background>
				</header>
			<!-- Billabong 17/4/13 F --> 
<object>C56A241F-42044BE7-86D96376-81ABCA8D</object> <!-- legs -->
<object>F001EE45-C5774015-96DB83F0-E67B0926</object> <!-- torso -->
<object>3DD134B3-58EF48E7-806214C4-E78FE8E9</object> <!-- torso -->
<object>BC35DB2A-F62D4996-B5960DD3-2425D7CD</object> <!-- bundle -->
<object>1617E036-D1634F53-9925E5E6-B7667917</object> <!-- bundle -->
		</node>
		</node>
			<node>
				<header>
				  <name lang="en-GB" default="true">nDreams</name>
				  <name lang="fr-FR" >nDreams</name>
				  <name lang="it-IT" >nDreams</name>
				  <name lang="de-DE" >nDreams</name>
				  <name lang="es-ES" >nDreams</name>
				  <thumbnail lang="en-GB" default="true">http://scee-home.playstation.net/e.home/hosted/CommercePoints/Thumbnails/ndreams.png</thumbnail>
				  <background lang="en-GB" default="true">http://scee-home.playstation.net/e.home/hosted/CommercePoints/Thumbnails/starsyellow_bg_scee.png</background>
				</header>
												 <node type="objects">
      <header>
        <name lang="en-GB" default="true">Animation</name>
        <name lang="fr-FR" >Animation</name>
        <name lang="it-IT" >Animazione</name>
        <name lang="de-DE" >Animation</name>
        <name lang="es-ES" >Animación</name>
        <thumbnail lang="en-GB" default="true" useOsdColour="true"> http://scee-home.playstation.net/e.home/hosted/CommercePoints/Thumbnails/animation.dds</thumbnail>
						<background lang="en-GB" default="true">http://scee-home.playstation.net/e.home/hosted/CommercePoints/Thumbnails/starsyellow_bg_scee.png</background>
      </header> 
<!--  Showoff anims --> 		
<object>BBD9DC0C-11764914-BE23D1E7-3ACE2829</object>
<object>E4C3A0B6-8BC54996-8BF82641-C0D5A57B</object>
<object>713EFBDC-18C3458D-9D80028F-CA3F108B</object>	
<!--  Breakdance Freeze anims --> 	
<object>A60B3C6B-0BB64FC9-9F63943E-442DE981</object>
<object>B30AC372-8A744BE6-8B193AE9-E4923BF9</object>
<object>4E03D0E6-F7034445-8CF51CD6-AF91D0B7</object>
				</node>
							<node type="objects">
		<header >
        <name lang="en-GB" default="true">Locomotion</name>
        <name lang="fr-FR" >Locomotion</name>
        <name lang="it-IT" >Locomotion</name>
        <name lang="de-DE" >Bewegung</name>
        <name lang="es-ES" >Locomoción</name>
        <thumbnail lang="en-GB" default="true" useOsdColour="true"> http://scee-home.playstation.net/e.home/hosted/CommercePoints/Thumbnails/locomotion.dds</thumbnail>
						<background lang="en-GB" default="true">http://scee-home.playstation.net/e.home/hosted/CommercePoints/Thumbnails/starsyellow_bg_scee.png</background>
		</header>		
<!-- nGear Locomotion cars -->
<object>5ED61AF9-895B486E-BC8734E3-6E2DAE98</object>
<object>203D5727-DB344CD5-B3825330-DA3B9CD1</object>
<object>0E3C9359-C0F24A10-B8CAAD37-92B5BC67</object>
<object>2E9A31CA-5F3B494D-97D1FBFF-E87C91E5</object>
<object>8D689D52-B52349A7-B66AAF2A-B7D09EB1</object>
<object>88AD1EF4-B0004D43-A1C580B5-86A49F36</object>
<object>89E09B73-25C644B1-B37F5330-45DB34E7</object>
<object>D6682DB2-67F24EDF-A605B674-055155BF</object>
<object>58CB69E7-E4C24567-B9D4736D-59C07928</object>
<object>09178B67-73FE4625-A059D5A0-E6175E1D</object>
<object>84895E90-61FF4848-B0999C6F-E85EFA6B</object>
<object>9C58B063-0CFB479E-A7C7CA7C-3E8D1DB0</object>
		 </node>
				</node>
				<node>
				<header>
				  <name lang="en-GB" default="true">nFashion</name>
				  <name lang="fr-FR" >nFashion</name>
				  <name lang="it-IT" >nFashion</name>
				  <name lang="de-DE" >nFashion</name>
				  <name lang="es-ES" >nFashion</name>
				  <thumbnail lang="en-GB" default="true">http://scee-home.playstation.net/e.home/hosted/CommercePoints/Thumbnails/nfashion_scee.png</thumbnail>
				  <background lang="en-GB" default="true">http://scee-home.playstation.net/e.home/hosted/CommercePoints/Thumbnails/starsyellow_bg_scee.png</background>
				</header>
										<node type="objects">
		<header >
        <name lang="en-GB" default="true">Locomotion</name>
        <name lang="fr-FR" >Locomotion</name>
        <name lang="it-IT" >Locomotion</name>
        <name lang="de-DE" >Bewegung</name>
        <name lang="es-ES" >Locomoción</name>
        <thumbnail lang="en-GB" default="true" useOsdColour="true"> http://scee-home.playstation.net/e.home/hosted/CommercePoints/Thumbnails/locomotion.dds</thumbnail>
						<background lang="en-GB" default="true">http://scee-home.playstation.net/e.home/hosted/CommercePoints/Thumbnails/starsyellow_bg_scee.png</background>
		</header>		
			<!-- nFashion Locomotion shoes-->
				<object>DCAA777F-F43446E7-9E33765E-5E1473AC</object>
<object>92BF8110-FC4D4383-BD9FACFF-FBAFA362</object>
<object>865BEF92-435E41B8-A07A0922-9266E32F</object>
<object>CD623944-7F0740F4-827D90BB-CCC3F45D</object>
<object>18F7A2B9-559E48CD-8DAF6A9E-7B97FAAA</object>
		 </node>
		 </node>
			<node>
		<header>
			<name lang="en-GB" default="true">Konami</name>
			<name lang="fr-FR">Konami</name>
			<name lang="de-DE">Konami</name>
			<name lang="it-IT">Konami</name>
			<name lang="es-ES">Konami</name>
			<thumbnail lang="en-GB" default="true" useOsdColour="false">http://scee-home.playstation.net/e.home/hosted/CommercePoints/Thumbnails/konami_scee.png</thumbnail>
						<background lang="en-GB" default="true">http://scee-home.playstation.net/e.home/hosted/CommercePoints/Thumbnails/starsyellow_bg_scee.png</background>
		</header>		
			<node type="objects">
		<header >
        <name lang="en-GB" default="true">Locomotion</name>
        <name lang="fr-FR" >Locomotion</name>
        <name lang="it-IT" >Locomotion</name>
        <name lang="de-DE" >Bewegung</name>
        <name lang="es-ES" >Locomoción</name>
        <thumbnail lang="en-GB" default="true" useOsdColour="true"> http://scee-home.playstation.net/e.home/hosted/CommercePoints/Thumbnails/locomotion.dds</thumbnail>
						<background lang="en-GB" default="true">http://scee-home.playstation.net/e.home/hosted/CommercePoints/Thumbnails/starsyellow_bg_scee.png</background>
		</header>		
				<!-- Aura #2 Locomotions -->
<object>C7CEDBEC-EDB04385-82A2F86D-9FF7C1A7</object>
<object>0072B2BF-89974A9F-8FAA019D-4CF69A27</object>
<object>8C54271B-24D74891-B2D2772E-A9E2F75C</object>
<object>464E3FA3-9F144666-B98AE32B-A9DC9D1C</object>
<object>0D27214E-CB1D4200-8E55D93F-DF449525</object>
<object>1E27A7A7-1E054C7E-AD871E46-4F0FF6E3</object>
<object>27927920-F1B341DB-B8F70A39-AD9E2960</object>
<object>82265D4E-D5CC43B9-B7611CAA-1F882FAC</object>
<object>8C4C95F0-EF174468-B0945F09-BE1D3CB4</object>
<object>A50D9977-E0144CBE-AD63E7DB-CB0E7FB8</object>
<object>A66B51F6-D22C4FEC-A1433CC7-C92CB1E0</object>
<object>0FC76960-97704B42-BFD31D7F-8E26EDE9</object>
<object>D951E1FC-84B94EB0-836DD39D-F08EA3EE</object>
<object>DD5409CC-6B5A4B15-B9AD1E6B-23C341E0</object>
		 </node>
		 	 </node>
		 	 			<node>
		<header>
			<name lang="en-GB" default="true">Deadly Premonition</name>
			<name lang="fr-FR">Deadly Premonition</name>
			<name lang="de-DE">Deadly Premonition</name>
			<name lang="it-IT">Deadly Premonition</name>
			<name lang="es-ES">Deadly Premonition</name>
			<thumbnail lang="en-GB" default="true" useOsdColour="false">http://scee-home.playstation.net/e.home/hosted/CommercePoints/Thumbnails/deadlypremonition_scee.png</thumbnail>
						<background lang="en-GB" default="true">http://scee-home.playstation.net/e.home/hosted/CommercePoints/Thumbnails/starsyellow_bg_scee.png</background>
		</header>		
			<node type="objects">
				<header>
					<name lang="en-GB" default="true">Male</name>
					<name lang="fr-FR">Homme</name>
					<name lang="de-DE">Männlich</name>
					<name lang="it-IT">Maschio</name>
					<name lang="es-ES">Hombre</name>
					<thumbnail lang="en-GB" default="true" useOsdColour="true">http://scee-home.playstation.net/e.home/hosted/CommercePoints/Thumbnails/male.dds</thumbnail>
						<background lang="en-GB" default="true">http://scee-home.playstation.net/e.home/hosted/CommercePoints/Thumbnails/starsyellow_bg_scee.png</background>
				</header>
			<!-- Deadly Premonition M --> 
<object>40B85B05-B6224869-841913D8-13D56DA1</object>
<object>F9983C70-37AA44F2-B6718D50-D3B791DE</object>
<object>7488ED66-77DF4B45-9E94E219-925C2439</object>
		</node>
			 	   <node type="objects">
				<header>
					<name lang="en-GB" default="true">Companions</name>
					<name lang="fr-FR" >Compagne</name>
					<name lang="it-IT" >Compagno</name>
					<name lang="de-DE" >Begleiter</name>
					<name lang="es-ES" >Comrade</name>
					<thumbnail lang="en-GB" default="true" useOsdColour="true">http://scee-home.playstation.net/e.home/hosted/CommercePoints/Thumbnails/companion.dds</thumbnail>
						<background lang="en-GB" default="true">http://scee-home.playstation.net/e.home/hosted/CommercePoints/Thumbnails/starsyellow_bg_scee.png</background>
				</header>
			<!-- Deadly Premonition Willie the Dog --> 
<object>A52D84C4-FB914210-B330369C-BD0F2B79</object>
			</node>
			<node type="objects">
		<header >
        <name lang="en-GB" default="true">Locomotion</name>
        <name lang="fr-FR" >Locomotion</name>
        <name lang="it-IT" >Locomotion</name>
        <name lang="de-DE" >Bewegung</name>
        <name lang="es-ES" >Locomoción</name>
        <thumbnail lang="en-GB" default="true" useOsdColour="true"> http://scee-home.playstation.net/e.home/hosted/CommercePoints/Thumbnails/locomotion.dds</thumbnail>
						<background lang="en-GB" default="true">http://scee-home.playstation.net/e.home/hosted/CommercePoints/Thumbnails/starsyellow_bg_scee.png</background>
		</header>		
<!-- Axe of Anguish Locomotion -->
<object>87E32C97-BE5143D7-B5313449-DBC0A08E</object>
		 </node>
		 	 </node>
				</node>
</commerce_point>
