<XML>
  <SCREEN ID="RBSkate_UpstairsTV">
    <TYPE>VIDEO</TYPE>
    <SOURCE>http://scee-home.playstation.net/e.home/mfe/content/05_01_2012/RedBullMississippiGrind2011.mp4</SOURCE>
  </SCREEN>
  <SCREEN ID="RBSkateJacuzziScreen">
    <TYPE>VIDEO</TYPE>
    <SOURCE>http://scee-home.playstation.net/e.home/mfe/content/05_01_2012/RedBullRivalsSkateSeattle2011.mp4</SOURCE>
  </SCREEN>
  <SCREEN ID="RBSkate_DownstairsTV">
    <TYPE>VIDEO</TYPE>
    <SOURCE>http://scee-home.playstation.net/e.home/mfe/content/05_01_2012/RedBullMississippiGrind2011.mp4</SOURCE>
  </SCREEN>
</XML>